setup.py
docs/CREDITS.TXT
docs/INSTALL.txt
docs/LICENSE.GPL
docs/LICENSE.txt
docs/TODO.txt
plonehrm/__init__.py
plonehrm.checklist.egg-info/PKG-INFO
plonehrm.checklist.egg-info/SOURCES.txt
plonehrm.checklist.egg-info/dependency_links.txt
plonehrm.checklist.egg-info/entry_points.txt
plonehrm.checklist.egg-info/namespace_packages.txt
plonehrm.checklist.egg-info/not-zip-safe
plonehrm.checklist.egg-info/requires.txt
plonehrm.checklist.egg-info/top_level.txt
plonehrm/checklist/HISTORY.txt
plonehrm/checklist/README.txt
plonehrm/checklist/__init__.py
plonehrm/checklist/config.py
plonehrm/checklist/configure.zcml
plonehrm/checklist/deprecation.zcml
plonehrm/checklist/interfaces.py
plonehrm/checklist/migration.py
plonehrm/checklist/permissions.zcml
plonehrm/checklist/rebuild_i18n.sh
plonehrm/checklist/tool.gif
plonehrm/checklist/version.txt
plonehrm/checklist/browser/__init__.py
plonehrm/checklist/browser/checklist.kss
plonehrm/checklist/browser/checklist.pt
plonehrm/checklist/browser/checklist.py
plonehrm/checklist/browser/checklist_kss.py
plonehrm/checklist/browser/checklisttool_edit.pt
plonehrm/checklist/browser/checklisttool_view.pt
plonehrm/checklist/browser/configure.zcml
plonehrm/checklist/browser/interfaces.py
plonehrm/checklist/browser/kss_tabbing.js
plonehrm/checklist/browser/simple_checklist.pt
plonehrm/checklist/content/__init__.py
plonehrm/checklist/content/checklist.py
plonehrm/checklist/content/tool.py
plonehrm/checklist/doc/checklist-technical.txt
plonehrm/checklist/doc/overview.txt
plonehrm/checklist/locales/checklist.pot
plonehrm/checklist/locales/en/LC_MESSAGES/checklist.po
plonehrm/checklist/locales/nl/LC_MESSAGES/checklist.po
plonehrm/checklist/locales/pt_BR/LC_MESSAGES/checklist.po
plonehrm/checklist/notifications/__init__.py
plonehrm/checklist/notifications/checkers.py
plonehrm/checklist/notifications/checklist_item.pt
plonehrm/checklist/notifications/configure.zcml
plonehrm/checklist/notifications/handlers.py
plonehrm/checklist/profiles/default/actionicons.xml
plonehrm/checklist/profiles/default/controlpanel.xml
plonehrm/checklist/profiles/default/factorytool.xml
plonehrm/checklist/profiles/default/kssregistry.xml
plonehrm/checklist/profiles/default/metadata.xml
plonehrm/checklist/profiles/default/propertiestool.xml
plonehrm/checklist/profiles/default/rolemap.xml
